[
  {
    "name": "Aliva Priva Jardin",
    "price": "47,043",
    "detail": "Jakarta Garden City Street, Cakung. Pulo Gadung, Jakarta Timur, DKI Jakarta",
    "image": "https://d2m3nfprmhqjvd.cloudfront.net/blog/20220228140845/Tata-Harrier-Black-Edition.jpg"
  },
  {
    "name": "Asatti Garden City",
    "price": "66,353",
    "detail": "Pahlawan Street XVII No.215, Cinangka, Sawangan, Depok, Jawa Barat",
    "image": "https://imgd.aeplcdn.com/664x374/n/cw/ec/134287/city-exterior-right-rear-three-quarter.jpeg?isig=0&q=80"
  },
  {
    "name": "Citralan Puri Serang",
    "price": "35,853",
    "detail": "Ruko Puri Indah Residence Block A7, Lingkar Street, Ciracas, Serang, Banten",
    "image": "https://image.cnbcfm.com/api/v1/image/107118551-2024-Mustang-18.jpg?v=1695177487"
  },
  {
    "name": "Aliva Priva Jardin",
    "price": "47,043",
    "detail": "Jakarta Garden City Street, Cakung. Pulo Gadung, Jakarta Timur, DKI Jakarta",
    "image": "https://e0.pxfuel.com/wallpapers/121/209/desktop-wallpaper-nissan-gtr-yellow-sports-car-nissan-gt-r-sports-2020.jpg"
  },
  {
    "name": "Asatti Garden City",
    "price": "66,353",
    "detail": "Pahlawan Street XVII No.215, Cinangka, Sawangan, Depok, Jawa Barat",
    "image": "https://carwow-uk-wp-3.imgix.net/18015-MC20BluInfinito-scaled-e1666008987698.jpg"
  },
  {
    "name": "Citralan Puri Serang",
    "price": "35,853",
    "detail": "Ruko Puri Indah Residence Block A7, Lingkar Street, Ciracas, Serang, Banten",
    "image": "https://www.motortrend.com/uploads/2022/08/2022-Bugatti-Chiron-Super-Sport-2-1.jpg"
  }
]
